<GaviData><Identifier>Country Context Nepal</Identifier><LanguageCode>1036</LanguageCode><DataTypeId>CCO</DataTypeId><ISOAlpha3>NPL</ISOAlpha3><DataSource>GAVI EDWH</DataSource><BuildDate>2019-09-17T19:30:12.060</BuildDate><DataSet><Name>Contexte national </Name><SourceName>GAVI</SourceName><SourceDate>2019-09-17T19:30:12.060</SourceDate><Data><Name>Population totale (2019)</Name><Value>29 854 378</Value></Data><Data><Name>Cohorte de naissance (2019)</Name><Value>579 279</Value></Data><Data><Name>Taux de mortalité des nourrissons (décès &lt; 1 an pour 1 000 naissances, 2015)</Name><Value>29/1000</Value></Data><Data><Name>Taux de mortalité infantile (décès &lt; 5 ans pour 1 000 naissances, 2015)</Name><Value>36/1000</Value></Data><Data><Name>Indice de la Banque mondiale, IDA (2015)</Name><Value>3,39</Value></Data><Data><Name>Revenu national brut (en US$ par habitant, 2015)</Name><Value>730</Value></Data><Data><Name>Nb de districts/territoires (2018) </Name><Value>77</Value></Data></DataSet></GaviData>