<GaviData><Identifier>Country Context Albania</Identifier><LanguageCode>2057</LanguageCode><DataTypeId>CCO</DataTypeId><ISOAlpha3>ALB</ISOAlpha3><DataSource>GAVI EDWH</DataSource><BuildDate>2019-09-17T18:54:09.347</BuildDate><DataSet><Name>Country context</Name><SourceName>GAVI</SourceName><SourceDate>2019-09-17T18:54:09.347</SourceDate><Data><Name>Total population (2019)</Name><Value>2877800.0</Value></Data><Data><Name>Birth cohort (2019)</Name><Value>40,311</Value></Data><Data><Name>Surviving Infants (surviving to 1 year per year, 2019)</Name><Value>32639.0</Value></Data><Data><Name>Infant mortality rate (deaths &lt; 1 year per 1000 births, 2015)</Name><Value>13/1000</Value></Data><Data><Name>Child mortality rate (deaths &lt; 5 years per 1000 births, 2015)</Name><Value>14/1000</Value></Data><Data><Name>Gross Nation Income (per capita US$, 2015)</Name><Value>5240.0</Value></Data><Data><Name>No. of districts/territories (2018)</Name><Value>36</Value></Data></DataSet></GaviData>