<GaviData><Identifier>Country Context Somalia</Identifier><LanguageCode>2057</LanguageCode><DataTypeId>CCO</DataTypeId><ISOAlpha3>SOM</ISOAlpha3><DataSource>GAVI EDWH</DataSource><BuildDate>2019-09-17T18:58:45.913</BuildDate><DataSet><Name>Country context</Name><SourceName>GAVI</SourceName><SourceDate>2019-09-17T18:58:45.913</SourceDate><Data><Name>Total population (2019)<Data><Name>Gross Nation Income (per capita US$, 2015)</Name><Value>nan</Value></Data><Data><Name>Surviving Infants (surviving to 1 year per year, 2019)</Name><Value>616683.0</Value></Data><Data><Name>Total population (2019)</Name><Value>15893219.0</Value></Data></Name><Value>12,067,829</Value></Data><Data><Name>Birth cohort (2019)</Name><Value>513,751</Value></Data><Data><Name>Infant mortality rate (deaths &lt; 1 year per 1000 births, 2015)</Name><Value>85/1000</Value></Data><Data><Name>Child mortality rate (deaths &lt; 5 years per 1000 births, 2015)</Name><Value>137/1000</Value></Data><Data><Name>No. of districts/territories (2018)</Name><Value>123</Value></Data></DataSet></GaviData>